passagefy/__init__.py
passagefy/admin.py
passagefy/apps.py
passagefy/filters.py
passagefy/models.py
passagefy/single.py
passagefy/tests.py
passagefy/urls.py
passagefy/views.py
passagefy/migrations/0001_initial.py
passagefy/migrations/0002_alter_feedback_created_at_alter_feedback_updated_at_and_more.py
passagefy/migrations/0003_alter_feedback_completion_rate.py
passagefy/migrations/__init__.py
passagefy-1.0.0.dist-info/licenses/LICENSE
passagefy-1.0.0.dist-info/METADATA
passagefy-1.0.0.dist-info/WHEEL
passagefy-1.0.0.dist-info/top_level.txt
passagefy-1.0.0.dist-info/RECORD
