Metadata-Version: 2.4
Name: passagefy
Version: 1.0.0
Summary: “通途”是一个基于Django的应用，帮助用户创建一个技术反馈表，并且与飞书的多维表格进行同步
Home-page: https://github.com/spirits001/passagefy
Author: 代码厨子
Author-email: hofeng@aqifun.com
Classifier: Programming Language :: Python :: 3
Classifier: License :: OSI Approved :: MIT License
Classifier: Operating System :: OS Independent
Requires-Python: >=3.7
License-File: LICENSE
Requires-Dist: django
Requires-Dist: djangorestframework
Requires-Dist: hadmin
Requires-Dist: django-filter
Requires-Dist: requests
Requires-Dist: djangorestframework-simplejwt
Dynamic: author
Dynamic: author-email
Dynamic: classifier
Dynamic: description
Dynamic: description-content-type
Dynamic: home-page
Dynamic: license-file
Dynamic: requires-dist
Dynamic: requires-python
Dynamic: summary
